dc_html_styler/__init__.py
dc_html_styler/dc_html_styler.py
dc_html_styler-0.1.3.dist-info/AUTHORS.rst
dc_html_styler-0.1.3.dist-info/LICENSE
dc_html_styler-0.1.3.dist-info/METADATA
dc_html_styler-0.1.3.dist-info/WHEEL
dc_html_styler-0.1.3.dist-info/top_level.txt
dc_html_styler-0.1.3.dist-info/RECORD
