Metadata-Version: 2.1
Name: dc-html-styler
Version: 0.1.3
Summary: Package for styling html-tables generated from Pandas DataFrames
Home-page: https://github.com/jejdc/dc_html_styler
Author: Jakob Erik Jensen
Author-email: jej@danskecommodities.com
License: MIT license
Keywords: dc_html_styler
Platform: UNKNOWN
Classifier: Development Status :: 2 - Pre-Alpha
Classifier: Intended Audience :: Developers
Classifier: License :: OSI Approved :: MIT License
Classifier: Natural Language :: English
Classifier: Programming Language :: Python :: 3
Classifier: Programming Language :: Python :: 3.5
Classifier: Programming Language :: Python :: 3.6
Classifier: Programming Language :: Python :: 3.7
Classifier: Programming Language :: Python :: 3.8
Requires-Python: >=3.5
Requires-Dist: cycler (==0.10.0)
Requires-Dist: Jinja2 (==2.11.3)
Requires-Dist: kiwisolver (==1.3.1)
Requires-Dist: MarkupSafe (==1.1.1)
Requires-Dist: matplotlib (==3.3.4)
Requires-Dist: numpy (==1.20.1)
Requires-Dist: pandas (==1.2.3)
Requires-Dist: Pillow (==8.1.2)
